README.txt
setup.py
src/mrs/__init__.py
src/mrs.developer.egg-info/PKG-INFO
src/mrs.developer.egg-info/SOURCES.txt
src/mrs.developer.egg-info/dependency_links.txt
src/mrs.developer.egg-info/entry_points.txt
src/mrs.developer.egg-info/namespace_packages.txt
src/mrs.developer.egg-info/not-zip-safe
src/mrs.developer.egg-info/requires.txt
src/mrs.developer.egg-info/top_level.txt
src/mrs/developer/__init__.py
src/mrs/developer/argparse.py
src/mrs/developer/base.py
src/mrs/developer/build.py
src/mrs/developer/console_script.py
src/mrs/developer/develop.py
src/mrs/developer/distributions.py
src/mrs/developer/extensions.py
src/mrs/developer/mrsd.py
src/mrs/developer/node.py
src/mrs/developer/testing.py
src/mrs/developer/tests/__init__.py
src/mrs/developer/tests/test_cmdline.py
src/mrs/developer/tests/test_node.py