Metadata-Version: 1.0
Name: mrs.developer
Version: 0
Summary: Mrs. Developer intends to be useful for developers.
Home-page: http://github.com/chaoflow/mrs.developer
Author: Florian Friesdorf
Author-email: flo@chaoflow.net
License: General Public Licence
Platform: UNKNOWN
Classifier: Development Status :: 3 - Alpha
Classifier: Framework :: Buildout
Classifier: Programming Language :: Python
Classifier: Topic :: Software Development :: Libraries :: Python Modules
